<?xml version="1.0" encoding="UTF-8" standalone="no"?>
<ProjectList>
  <projects>
    <renovation>true</renovation>
    <address>kamtjatka 13</address>
    <buildingSize>24.0</buildingSize>
    <totalHours>30</totalHours>
    <endDate>
      <month>6</month>
      <year>2024</year>
      <day>7</day>
    </endDate>
    <otherRoomsWithPlumbing>0</otherRoomsWithPlumbing>
    <totalExpenses>400000.0</totalExpenses>
    <completed>false</completed>
    <bathrooms>2</bathrooms>
    <title>Project TR</title>
    <type>Residential building</type>
    <budgetMax>10000.0</budgetMax>
    <kitchens>1</kitchens>
    <expectedExpenses>0.0</expectedExpenses>
    <expectedHours>0</expectedHours>
    <timeline>6</timeline>
    <budgetMin>5000.0</budgetMin>
    <startDate>
      <month>12</month>
      <year>2023</year>
      <day>7</day>
    </startDate>
    <customer>
      <emailAddress>bozo@gmail.com</emailAddress>
      <phoneNumber>+4512345678</phoneNumber>
      <name>bozo</name>
    </customer>
  </projects>
  <projects>
    <renovation>false</renovation>
    <address>kamtjatka 14</address>
    <buildingSize>24.0</buildingSize>
    <totalHours>0</totalHours>
    <endDate>
      <month>6</month>
      <year>2024</year>
      <day>7</day>
    </endDate>
    <otherRoomsWithPlumbing>0</otherRoomsWithPlumbing>
    <totalExpenses>0.0</totalExpenses>
    <completed>false</completed>
    <bathrooms>2</bathrooms>
    <title>Project PS</title>
    <type>Residential building</type>
    <budgetMax>10000.0</budgetMax>
    <kitchens>1</kitchens>
    <expectedExpenses>0.0</expectedExpenses>
    <expectedHours>0</expectedHours>
    <timeline>6</timeline>
    <budgetMin>5000.0</budgetMin>
    <startDate>
      <month>12</month>
      <year>2023</year>
      <day>7</day>
    </startDate>
    <customer>
      <emailAddress>bozo@gmail.com</emailAddress>
      <phoneNumber>+4512345678</phoneNumber>
      <name>bozo</name>
    </customer>
  </projects>
  <projects>
    <renovation>false</renovation>
    <address>horsens</address>
    <buildingSize>24.0</buildingSize>
    <totalHours>2000</totalHours>
    <endDate>
      <month>6</month>
      <year>2024</year>
      <day>7</day>
    </endDate>
    <otherRoomsWithPlumbing>0</otherRoomsWithPlumbing>
    <totalExpenses>250000.0</totalExpenses>
    <completed>true</completed>
    <bathrooms>2</bathrooms>
    <title>Project IL</title>
    <type>Residential building</type>
    <budgetMax>10000.0</budgetMax>
    <kitchens>1</kitchens>
    <expectedExpenses>0.0</expectedExpenses>
    <expectedHours>0</expectedHours>
    <timeline>6</timeline>
    <budgetMin>5000.0</budgetMin>
    <startDate>
      <month>12</month>
      <year>2023</year>
      <day>7</day>
    </startDate>
    <customer>
      <emailAddress>bozo@gmail.com</emailAddress>
      <phoneNumber>+4512345678</phoneNumber>
      <name>bozo</name>
    </customer>
  </projects>
  <projects>
    <address>aarhus</address>
    <buildingSize>2000.0</buildingSize>
    <totalHours>300</totalHours>
    <endDate>
      <month>3</month>
      <year>2024</year>
      <day>7</day>
    </endDate>
    <totalExpenses>0.0</totalExpenses>
    <completed>false</completed>
    <title>Project BI</title>
    <type>Commercial building</type>
    <budgetMax>5.0</budgetMax>
    <floors>2</floors>
    <expectedExpenses>540000.0</expectedExpenses>
    <expectedHours>0</expectedHours>
    <intendedUse>big ahh store</intendedUse>
    <timeline>3</timeline>
    <budgetMin>1.0</budgetMin>
    <startDate>
      <month>12</month>
      <year>2023</year>
      <day>7</day>
    </startDate>
    <customer>
      <emailAddress>bilka@bilka.com</emailAddress>
      <phoneNumber>-450987654</phoneNumber>
      <name>bilka</name>
    </customer>
  </projects>
  <projects>
    <renovation>true</renovation>
    <address>123 Main St</address>
    <buildingSize>1500.0</buildingSize>
    <totalHours>254</totalHours>
    <endDate>
      <month>12</month>
      <year>2024</year>
      <day>7</day>
    </endDate>
    <otherRoomsWithPlumbing>3</otherRoomsWithPlumbing>
    <totalExpenses>12000.0</totalExpenses>
    <completed>false</completed>
    <bathrooms>2</bathrooms>
    <title>Project HO</title>
    <type>Residential building</type>
    <budgetMax>200000.0</budgetMax>
    <kitchens>2</kitchens>
    <expectedExpenses>0.0</expectedExpenses>
    <expectedHours>0</expectedHours>
    <timeline>12</timeline>
    <budgetMin>100000.0</budgetMin>
    <startDate>
      <month>12</month>
      <year>2023</year>
      <day>7</day>
    </startDate>
    <customer>
      <emailAddress>john.doe@email.com</emailAddress>
      <phoneNumber>123-456-7890</phoneNumber>
      <name>John Doe</name>
    </customer>
  </projects>
  <projects>
    <renovation>false</renovation>
    <address>456 Oak St</address>
    <buildingSize>1000.0</buildingSize>
    <totalHours>67</totalHours>
    <endDate>
      <month>10</month>
      <year>2024</year>
      <day>7</day>
    </endDate>
    <otherRoomsWithPlumbing>2</otherRoomsWithPlumbing>
    <totalExpenses>12400.0</totalExpenses>
    <completed>false</completed>
    <bathrooms>1</bathrooms>
    <title>Project AP</title>
    <type>Residential building</type>
    <budgetMax>150000.0</budgetMax>
    <kitchens>1</kitchens>
    <expectedExpenses>0.0</expectedExpenses>
    <expectedHours>0</expectedHours>
    <timeline>10</timeline>
    <budgetMin>80000.0</budgetMin>
    <startDate>
      <month>12</month>
      <year>2023</year>
      <day>7</day>
    </startDate>
    <customer>
      <emailAddress>jane.smith@email.com</emailAddress>
      <phoneNumber>987-654-3210</phoneNumber>
      <name>Jane Smith</name>
    </customer>
  </projects>
  <projects>
    <address>789 Industrial Blvd</address>
    <facilityType>Manufacturing</facilityType>
    <totalHours>53</totalHours>
    <endDate>
      <month>6</month>
      <year>2025</year>
      <day>7</day>
    </endDate>
    <totalExpenses>0.0</totalExpenses>
    <completed>false</completed>
    <title>Project SL(udge)</title>
    <type>Industrial facility</type>
    <budgetMax>1000000.0</budgetMax>
    <facilitySize>2500.0</facilitySize>
    <expectedExpenses>98000.0</expectedExpenses>
    <expectedHours>0</expectedHours>
    <timeline>18</timeline>
    <budgetMin>500000.0</budgetMin>
    <startDate>
      <month>12</month>
      <year>2023</year>
      <day>7</day>
    </startDate>
    <customer>
      <emailAddress>michael.johnson@email.com</emailAddress>
      <phoneNumber>555-1234</phoneNumber>
      <name>Michael Johnson</name>
    </customer>
  </projects>
  <projects>
    <address>101 Logistics St</address>
    <facilityType>Storage</facilityType>
    <totalHours>120</totalHours>
    <endDate>
      <month>3</month>
      <year>2025</year>
      <day>7</day>
    </endDate>
    <totalExpenses>0.0</totalExpenses>
    <completed>false</completed>
    <title>Project ST</title>
    <type>Industrial facility</type>
    <budgetMax>800000.0</budgetMax>
    <facilitySize>1200.0</facilitySize>
    <expectedExpenses>10000.0</expectedExpenses>
    <expectedHours>0</expectedHours>
    <timeline>15</timeline>
    <budgetMin>300000.0</budgetMin>
    <startDate>
      <month>12</month>
      <year>2023</year>
      <day>7</day>
    </startDate>
    <customer>
      <emailAddress>emily.davis@email.com</emailAddress>
      <phoneNumber>555-5678</phoneNumber>
      <name>Emily Davis</name>
    </customer>
  </projects>
  <projects>
    <bridgesOrTunnels>2</bridgesOrTunnels>
    <address>Horsens</address>
    <totalHours>33</totalHours>
    <endDate>
      <month>10</month>
      <year>2024</year>
      <day>7</day>
    </endDate>
    <length>2000.0</length>
    <totalExpenses>450000.0</totalExpenses>
    <completed>true</completed>
    <title>Project AX</title>
    <type>Road construction</type>
    <budgetMax>4000.0</budgetMax>
    <expectedExpenses>0.0</expectedExpenses>
    <expectedHours>0</expectedHours>
    <width>30.0</width>
    <timeline>10</timeline>
    <budgetMin>2000.0</budgetMin>
    <startDate>
      <month>12</month>
      <year>2023</year>
      <day>7</day>
    </startDate>
    <customer>
      <emailAddress>angela@gmail.com</emailAddress>
      <phoneNumber>738 192 253</phoneNumber>
      <name>Angela Cebrian</name>
    </customer>
  </projects>
  <projects>
    <bridgesOrTunnels>1</bridgesOrTunnels>
    <address>Silkeborg</address>
    <totalHours>0</totalHours>
    <endDate>
      <month>12</month>
      <year>2024</year>
      <day>7</day>
    </endDate>
    <length>100.0</length>
    <totalExpenses>0.0</totalExpenses>
    <completed>false</completed>
    <title>Project LP</title>
    <type>Road construction</type>
    <budgetMax>20000.0</budgetMax>
    <expectedExpenses>0.0</expectedExpenses>
    <expectedHours>0</expectedHours>
    <width>3.0</width>
    <timeline>12</timeline>
    <budgetMin>5000.0</budgetMin>
    <startDate>
      <month>12</month>
      <year>2023</year>
      <day>7</day>
    </startDate>
    <customer>
      <emailAddress>joan@gmail.com</emailAddress>
      <phoneNumber>420 692 243</phoneNumber>
      <name>Joan Hageneier</name>
    </customer>
  </projects>
  <titles>Project TR</titles>
  <titles>Project PS</titles>
  <titles>Project IL</titles>
  <titles>Project BI</titles>
  <titles>Project HO</titles>
  <titles>Project AP</titles>
  <titles>Project SL(udge)</titles>
  <titles>Project ST</titles>
  <titles>Project AX</titles>
  <titles>Project LP</titles>
</ProjectList>
